github_release_retry/__init__.py
github_release_retry/github_release_retry.py
github_release_retry/py.typed
github_release_retry2-1.1.0.dist-info/AUTHORS
github_release_retry2-1.1.0.dist-info/LICENSE
github_release_retry2-1.1.0.dist-info/METADATA
github_release_retry2-1.1.0.dist-info/WHEEL
github_release_retry2-1.1.0.dist-info/entry_points.txt
github_release_retry2-1.1.0.dist-info/top_level.txt
github_release_retry2-1.1.0.dist-info/RECORD
